complycube/__init__.py
complycube/complycube.py
complycube/error.py
complycube/eventverifier.py
complycube/util.py
complycube/api_resource_actions/__init__.py
complycube/api_resource_actions/createresource.py
complycube/api_resource_actions/deleteresource.py
complycube/api_resource_actions/getresource.py
complycube/api_resource_actions/listresource.py
complycube/api_resource_actions/updateresource.py
complycube/api_resources/__init__.py
complycube/api_resources/accountinfo.py
complycube/api_resources/address.py
complycube/api_resources/auditlog.py
complycube/api_resources/check.py
complycube/api_resources/client.py
complycube/api_resources/complycuberesource.py
complycube/api_resources/document.py
complycube/api_resources/flow.py
complycube/api_resources/livephoto.py
complycube/api_resources/livevideo.py
complycube/api_resources/report.py
complycube/api_resources/riskprofile.py
complycube/api_resources/static.py
complycube/api_resources/teammember.py
complycube/api_resources/token.py
complycube/api_resources/webhook.py
complycube/api_resources/workflowsessions.py
complycube/model/__init__.py
complycube/model/accountinfo.py
complycube/model/address.py
complycube/model/auditlog.py
complycube/model/check.py
complycube/model/client.py
complycube/model/complycubecollection.py
complycube/model/complycubeobject.py
complycube/model/document.py
complycube/model/flow.py
complycube/model/livephoto.py
complycube/model/livevideo.py
complycube/model/report.py
complycube/model/riskprofile.py
complycube/model/teammember.py
complycube/model/token.py
complycube/model/webhook.py
complycube/model/workflowsession.py
complycube-1.1.8.dist-info/licenses/LICENSE
complycube-1.1.8.dist-info/METADATA
complycube-1.1.8.dist-info/WHEEL
complycube-1.1.8.dist-info/top_level.txt
complycube-1.1.8.dist-info/RECORD
