Metadata-Version: 2.4
Name: complycube
Version: 1.1.8
Summary: Official Python client for the ComplyCube API
Author: Complycube
Author-email: tech@complycube.com
Keywords: complycube,aml,kyc,client,api,wrapper,PEP,identity verification,identity checks,document verification
Classifier: Intended Audience :: Developers
Classifier: Intended Audience :: Telecommunications Industry
Classifier: Intended Audience :: Financial and Insurance Industry
Classifier: Intended Audience :: Information Technology
Classifier: Intended Audience :: Legal Industry
Classifier: Topic :: Software Development :: Libraries :: Python Modules
Classifier: Programming Language :: Python :: 3.6
Classifier: Programming Language :: Python :: 3.7
Classifier: Programming Language :: Python :: 3.8
Classifier: Programming Language :: Python :: 3.9
Classifier: Programming Language :: Python :: 3.10
Classifier: Programming Language :: Python :: 3.11
Classifier: Programming Language :: Python :: 3.12
Classifier: Operating System :: OS Independent
Requires-Python: >=3.6
License-File: LICENSE
Requires-Dist: requests>=2.20.0
Requires-Dist: pyhumps>=1.2.0
Requires-Dist: urllib3>=1.26
Dynamic: license-file
